AUTHORS
ChangeLog
LICENSE
README.rst
setup.cfg
setup.py
celerybeat_callargs.egg-info/PKG-INFO
celerybeat_callargs.egg-info/SOURCES.txt
celerybeat_callargs.egg-info/dependency_links.txt
celerybeat_callargs.egg-info/not-zip-safe
celerybeat_callargs.egg-info/pbr.json
celerybeat_callargs.egg-info/top_level.txt
celerybeatcallargs/__init__.py