Metadata-Version: 1.0
Name: celerybeat-callargs
Version: 0.0.1
Summary: Celerybeat scheduler for tasks with callable args
Home-page: UNKNOWN
Author: UNKNOWN
Author-email: UNKNOWN
License: UNKNOWN
Platform: UNKNOWN
